databricks/__init__.py
databricks/labs/__init__.py
databricks/labs/lsql/__about__.py
databricks/labs/lsql/__init__.py
databricks/labs/lsql/__main__.py
databricks/labs/lsql/backends.py
databricks/labs/lsql/cli.py
databricks/labs/lsql/core.py
databricks/labs/lsql/dashboards.py
databricks/labs/lsql/deployment.py
databricks/labs/lsql/escapes.py
databricks/labs/lsql/py.typed
databricks/labs/lsql/structs.py
databricks/labs/lsql/lakeview/.codegen.json
databricks/labs/lsql/lakeview/__init__.py
databricks/labs/lsql/lakeview/model.py
databricks/labs/lsql/lakeview/model.py.tmpl
databricks/labs/lsql/lakeview/polymorphism.py
databricks_labs_lsql-0.16.0.dist-info/METADATA
databricks_labs_lsql-0.16.0.dist-info/WHEEL
databricks_labs_lsql-0.16.0.dist-info/licenses/LICENSE
databricks_labs_lsql-0.16.0.dist-info/licenses/NOTICE
databricks_labs_lsql-0.16.0.dist-info/RECORD
