Metadata-Version: 2.4
Name: databricks-labs-lsql
Version: 0.16.0
Summary: Lightweight stateless SQL execution for Databricks with minimal dependencies
Project-URL: Documentation, https://github.com/databrickslabs/lsql#readme
Project-URL: Issues, https://github.com/databrickslabs/lsql/issues
Project-URL: Source, https://github.com/databrickslabs/lsql
Author-email: Serge Smertin <serge.smertin@databricks.com>
License-File: LICENSE
License-File: NOTICE
Classifier: Development Status :: 3 - Alpha
Classifier: License :: Other/Proprietary License
Classifier: Programming Language :: Python
Classifier: Programming Language :: Python :: 3.10
Classifier: Programming Language :: Python :: 3.11
Classifier: Programming Language :: Python :: 3.12
Classifier: Programming Language :: Python :: Implementation :: CPython
Classifier: Programming Language :: Python :: Implementation :: PyPy
Requires-Python: >=3.10
Requires-Dist: databricks-labs-blueprint[yaml]>=0.4.2
Requires-Dist: databricks-sdk<1.0.0,>=0.38.0
Requires-Dist: sqlglot>=22.3.1
